fiveoneone/__init__.py
fiveoneone/agency.py
fiveoneone/departure.py
fiveoneone/exceptions.py
fiveoneone/model.py
fiveoneone/route.py
fiveoneone/stop.py
fiveoneone-0.6.0.dist-info/LICENSE
fiveoneone-0.6.0.dist-info/METADATA
fiveoneone-0.6.0.dist-info/WHEEL
fiveoneone-0.6.0.dist-info/top_level.txt
fiveoneone-0.6.0.dist-info/RECORD
