Metadata-Version: 2.1
Name: fiveoneone
Version: 0.6.0
Summary: A python API to consume transit data from http://511.org.
Home-page: https://github.com/rberrelleza/511-transit
Author: Ramiro Berrelleza
Author-email: rberrelleza@gmail.com
License: MIT
Platform: any
Classifier: Environment :: Web Environment
Classifier: Intended Audience :: Developers
Classifier: License :: OSI Approved :: BSD License
Classifier: Operating System :: OS Independent
Classifier: Programming Language :: Python :: 3
Classifier: Topic :: Internet :: WWW/HTTP :: Dynamic Content
Classifier: Topic :: Software Development :: Libraries :: Python Modules
Requires-Dist: requests (>=2.22)
